docs/source/conf.py
examples/__init__.py
examples/binary.py
examples/classification_unknown_length_objectives.py
examples/coevolution_dna.py
examples/example.py
examples/extra_columns_example.py
examples/logging_example.py
examples/multi_target_lexicase.py
examples/pcfg_example.py
examples/recurrence.py
examples/stack.py
examples/synthetic_grammar_example.py
examples/tutorial_example.py
examples/benchmarks/__init__.py
examples/benchmarks/benchmark.py
examples/benchmarks/benchmark_suite.py
examples/benchmarks/classification.py
examples/benchmarks/classification_lexicase.py
examples/benchmarks/datasets.py
examples/benchmarks/domino.py
examples/benchmarks/game_of_life_vectorial.py
examples/benchmarks/pymax.py
examples/benchmarks/regression.py
examples/benchmarks/regression_lexicase.py
examples/benchmarks/santafe.py
examples/benchmarks/string_match.py
examples/benchmarks/vectorialgp.py
examples/data/__init__.py
examples/data/manipulate_data.py
examples/data/Banknote/__init__.py
examples/geml/classifier_example.py
examples/geml/regressor_example.py
examples/genetic_example/genetic_example.py
examples/progsys/Median.py
examples/progsys/Number_IO.py
examples/progsys/Smallest.py
examples/progsys/Sum_of_Squares.py
examples/progsys/Vector_Average.py
examples/progsys/__init__.py
examples/progsys/utils.py
examples/progsys/embed/Median.py
examples/progsys/embed/Number_IO.py
examples/progsys/embed/Smallest.py
examples/progsys/embed/Sum_of_Squares.py
examples/progsys/embed/Vector_Average.py
examples/progsys/embed/__init__.py
geml/__init__.py
geml/classifiers.py
geml/common.py
geml/regressors.py
geml/simplegp.py
geml/grammars/__init__.py
geml/grammars/basic_math.py
geml/grammars/letter.py
geml/grammars/literals.py
geml/grammars/regex.py
geml/grammars/ruleset_classification.py
geml/grammars/sgp.py
geml/grammars/symbolic_regression.py
geml/grammars/coding/__init__.py
geml/grammars/coding/classes.py
geml/grammars/coding/conditions.py
geml/grammars/coding/control_flow.py
GeneticEngine-0.9.0.dist-info/METADATA
GeneticEngine-0.9.0.dist-info/WHEEL
GeneticEngine-0.9.0.dist-info/top_level.txt
GeneticEngine-0.9.0.dist-info/RECORD
