Metadata-Version: 2.1
Name: GeneticEngine
Version: 0.9.0
Summary: Genetic Programming with Types and Grammars
Author-email: Guilherme Espada <gjespada@fc.ul.pt>, Leon Ingelse <leoningelse@gmail.com>, Paulo Santos <pacsantos@fc.ul.pt>, Pedro Barbosa <psbarbosa@ciencias.ulisboa.pt>, Alcides Fonseca <me@alcidesfonseca.com>
License: https://opensource.org/licenses/MIT
Project-URL: homepage, https://github.com/alcides/GeneticEngine/
Project-URL: repository, https://github.com/alcides/GeneticEngine/
Project-URL: documentation, https://github.com/alcides/GeneticEngine/
Keywords: evolutionary computation,genetic programming,regression,machine learning
Classifier: Development Status :: 4 - Beta
Classifier: Programming Language :: Python :: 3.10
Classifier: Programming Language :: Python :: 3.11
Classifier: Programming Language :: Python :: 3.12
Classifier: Programming Language :: Python :: 3.13
Requires-Python: >=3.10
Requires-Dist: dill==0.3.9
Requires-Dist: lark==1.2.2
Requires-Dist: loguru==0.7.2
Requires-Dist: numpy==2.1.3
Requires-Dist: palettable==3.3.3
Requires-Dist: pandas==2.2.3
Requires-Dist: pathos==0.3.3
Requires-Dist: polyleven==0.8
Requires-Dist: pytest==8.3.4
Requires-Dist: pytest-benchmark==5.1.0
Requires-Dist: scikit-learn==1.5.2
Requires-Dist: seaborn==0.13.2
Requires-Dist: sympy==1.13.3
Requires-Dist: threadpoolctl==3.5.0
Requires-Dist: z3-solver==4.13.3.0
